<?xml version="1.0" encoding="UTF-8"?>
 <odoo>
    <data>
        <!-- Add field to existing view -->
        <record model="ir.ui.view" id="partner_check_phone_form_view">
            <field name="model">res.partner</field>
            <field name="inherit_id" ref="base.view_partner_form"/>
            <field name="arch" type="xml">
                <field name="phone" position="before">
                        <field name="phone_country_id"  class="oe_inline" options="{&quot;no_open&quot;: True, &quot;no_create&quot;: True}"/>
                </field>
                <field name="mobile" position="before">
                        <field name="mobile_country_id"  class="oe_inline" options="{&quot;no_open&quot;: True, &quot;no_create&quot;: True}"/>
                </field>
            </field>
        </record>


        <!--<record model="ir.actions.act_window" id="contact_list_action">-->
            <!--<field name="name">Contacts</field>-->
            <!--<field name="res_model">res.partner</field>-->
            <!--<field name="view_mode">tree,form</field>-->
        <!--</record>-->

    </data>
</odoo>
